{
  "version": "3.0.3",
  "flags": {},
  "shapes": [
    {
      "kie_linking": [],
      "label": "开关箱",
      "score": null,
      "points": [
        [
          843.5294117647059,
          599.4117647058823
        ],
        [
          907.0588235294119,
          704.1176470588235
        ]
      ],
      "group_id": null,
      "description": "",
      "difficult": false,
      "shape_type": "rectangle",
      "flags": {},
      "attributes": {}
    },
    {
      "kie_linking": [],
      "label": "人员",
      "score": null,
      "points": [
        [
          728.2352941176471,
          287.64705882352945
        ],
        [
          777.6470588235295,
          418.2352941176471
        ]
      ],
      "group_id": null,
      "description": "",
      "difficult": false,
      "shape_type": "rectangle",
      "flags": {},
      "attributes": {}
    },
    {
      "kie_linking": [],
      "label": "反光衣",
      "score": null,
      "points": [
        [
          738.8235294117646,
          294.70588235294116
        ],
        [
          767.0588235294117,
          320.5882352941177
        ]
      ],
      "group_id": null,
      "description": "",
      "difficult": false,
      "shape_type": "rectangle",
      "flags": {},
      "attributes": {}
    },
    {
      "kie_linking": [],
      "label": "临边防护",
      "score": null,
      "points": [
        [
          1137.6470588235295,
          1072.3529411764705
        ],
        [
          1101.1764705882354,
          1077.0588235294117
        ],
        [
          1034.1176470588236,
          971.1764705882352
        ],
        [
          794.1176470588236,
          439.4117647058824
        ],
        [
          669.4117647058824,
          150.0
        ],
        [
          601.1764705882354,
          2.9411764705882355
        ],
        [
          630.5882352941176,
          1.7647058823529411
        ],
        [
          645.8823529411766,
          37.05882352941177
        ],
        [
          677.6470588235295,
          98.23529411764706
        ],
        [
          812.9411764705883,
          382.94117647058823
        ],
        [
          920.0,
          594.7058823529411
        ],
        [
          1077.6470588235295,
          913.5294117647059
        ]
      ],
      "group_id": null,
      "description": "",
      "difficult": false,
      "shape_type": "polygon",
      "flags": {},
      "attributes": {}
    },
    {
      "kie_linking": [],
      "label": "人员",
      "score": null,
      "points": [
        [
          541.1764705882354,
          80.58823529411765
        ],
        [
          582.3529411764705,
          159.41176470588235
        ]
      ],
      "group_id": null,
      "description": "",
      "difficult": false,
      "shape_type": "rectangle",
      "flags": {},
      "attributes": {}
    },
    {
      "kie_linking": [],
      "label": "安全帽",
      "score": null,
      "points": [
        [
          550.5882352941176,
          81.76470588235294
        ],
        [
          569.4117647058824,
          97.05882352941177
        ]
      ],
      "group_id": null,
      "description": "",
      "difficult": false,
      "shape_type": "rectangle",
      "flags": {},
      "attributes": {}
    },
    {
      "kie_linking": [],
      "label": "反光衣",
      "score": null,
      "points": [
        [
          552.9411764705883,
          102.94117647058825
        ],
        [
          576.4705882352941,
          133.52941176470588
        ]
      ],
      "group_id": null,
      "description": "",
      "difficult": false,
      "shape_type": "rectangle",
      "flags": {},
      "attributes": {}
    },
    {
      "kie_linking": [],
      "label": "人员",
      "score": null,
      "points": [
        [
          627.0588235294117,
          79.41176470588236
        ],
        [
          671.7647058823529,
          191.1764705882353
        ]
      ],
      "group_id": null,
      "description": "",
      "difficult": false,
      "shape_type": "rectangle",
      "flags": {},
      "attributes": {}
    },
    {
      "kie_linking": [],
      "label": "安全帽",
      "score": null,
      "points": [
        [
          645.8823529411766,
          91.1764705882353
        ],
        [
          665.8823529411766,
          107.64705882352942
        ]
      ],
      "group_id": null,
      "description": "",
      "difficult": false,
      "shape_type": "rectangle",
      "flags": {},
      "attributes": {}
    },
    {
      "kie_linking": [],
      "label": "反光衣",
      "score": null,
      "points": [
        [
          632.9411764705883,
          110.0
        ],
        [
          654.1176470588234,
          147.64705882352942
        ]
      ],
      "group_id": null,
      "description": "",
      "difficult": false,
      "shape_type": "rectangle",
      "flags": {},
      "attributes": {}
    },
    {
      "kie_linking": [],
      "label": "人员",
      "score": null,
      "points": [
        [
          687.0588235294117,
          205.29411764705884
        ],
        [
          725.8823529411766,
          319.4117647058824
        ]
      ],
      "group_id": null,
      "description": "",
      "difficult": false,
      "shape_type": "rectangle",
      "flags": {},
      "attributes": {}
    },
    {
      "kie_linking": [],
      "label": "安全帽",
      "score": null,
      "points": [
        [
          702.3529411764705,
          208.82352941176472
        ],
        [
          721.1764705882354,
          228.82352941176472
        ]
      ],
      "group_id": null,
      "description": "",
      "difficult": false,
      "shape_type": "rectangle",
      "flags": {},
      "attributes": {}
    },
    {
      "kie_linking": [],
      "label": "反光衣",
      "score": null,
      "points": [
        [
          692.9411764705883,
          234.7058823529412
        ],
        [
          716.4705882352941,
          270.0
        ]
      ],
      "group_id": null,
      "description": "",
      "difficult": false,
      "shape_type": "rectangle",
      "flags": {},
      "attributes": {}
    },
    {
      "kie_linking": [],
      "label": "人员",
      "score": null,
      "points": [
        [
          732.9411764705883,
          186.47058823529412
        ],
        [
          780.0,
          282.94117647058823
        ]
      ],
      "group_id": null,
      "description": "",
      "difficult": false,
      "shape_type": "rectangle",
      "flags": {},
      "attributes": {}
    },
    {
      "kie_linking": [],
      "label": "安全帽",
      "score": null,
      "points": [
        [
          741.1764705882354,
          187.64705882352942
        ],
        [
          758.8235294117646,
          208.82352941176472
        ]
      ],
      "group_id": null,
      "description": "",
      "difficult": false,
      "shape_type": "rectangle",
      "flags": {},
      "attributes": {}
    },
    {
      "kie_linking": [],
      "label": "反光衣",
      "score": null,
      "points": [
        [
          749.4117647058824,
          214.7058823529412
        ],
        [
          770.5882352941176,
          251.1764705882353
        ]
      ],
      "group_id": null,
      "description": "",
      "difficult": false,
      "shape_type": "rectangle",
      "flags": {},
      "attributes": {}
    },
    {
      "kie_linking": [],
      "label": "洒水车",
      "score": null,
      "points": [
        [
          104.70588235294116,
          5.294117647058824
        ],
        [
          312.94117647058823,
          252.3529411764706
        ]
      ],
      "group_id": null,
      "description": "",
      "difficult": false,
      "shape_type": "rectangle",
      "flags": {},
      "attributes": {}
    },
    {
      "kie_linking": [],
      "label": "越野车",
      "score": null,
      "points": [
        [
          529.4117647058824,
          144.11764705882354
        ],
        [
          681.1764705882354,
          317.05882352941177
        ]
      ],
      "group_id": null,
      "description": "",
      "difficult": false,
      "shape_type": "rectangle",
      "flags": {},
      "attributes": {}
    },
    {
      "kie_linking": [],
      "label": "越野车",
      "score": null,
      "points": [
        [
          500.00000000000006,
          19.411764705882355
        ],
        [
          622.3529411764705,
          133.52941176470588
        ]
      ],
      "group_id": null,
      "description": "",
      "difficult": false,
      "shape_type": "rectangle",
      "flags": {},
      "attributes": {}
    },
    {
      "label": "电缆线",
      "score": null,
      "points": [
        [
          863.0232558139537,
          711.5116279069767
        ],
        [
          871.1627906976746,
          770.813953488372
        ],
        [
          906.0465116279072,
          824.3023255813953
        ],
        [
          933.953488372093,
          871.9767441860465
        ],
        [
          972.325581395349,
          927.7906976744185
        ],
        [
          1006.0465116279072,
          980.1162790697674
        ],
        [
          1045.5813953488373,
          1039.418604651163
        ],
        [
          1065.3488372093025,
          1031.279069767442
        ],
        [
          1010.6976744186047,
          927.7906976744185
        ],
        [
          944.4186046511629,
          831.2790697674418
        ],
        [
          896.7441860465117,
          749.8837209302325
        ],
        [
          883.953488372093,
          709.1860465116279
        ]
      ],
      "group_id": null,
      "description": "",
      "difficult": false,
      "shape_type": "polygon",
      "flags": {},
      "attributes": {},
      "kie_linking": []
    }
  ],
  "imagePath": "dji_fly_20251112_100017_0_1762912817126_photo_low_quality.jpg",
  "imageData": null,
  "imageHeight": 1080,
  "imageWidth": 1440,
  "description": ""
}