{
  "version": "3.0.3",
  "flags": {},
  "shapes": [
    {
      "kie_linking": [],
      "label": "人员",
      "score": null,
      "points": [
        [
          780.0,
          598.2352941176471
        ],
        [
          812.9411764705883,
          647.6470588235294
        ]
      ],
      "group_id": null,
      "description": "",
      "difficult": false,
      "shape_type": "rectangle",
      "flags": {},
      "attributes": {}
    },
    {
      "kie_linking": [],
      "label": "摩托车",
      "score": null,
      "points": [
        [
          747.0588235294117,
          578.2352941176471
        ],
        [
          832.9411764705883,
          701.7647058823529
        ]
      ],
      "group_id": null,
      "description": "",
      "difficult": false,
      "shape_type": "rectangle",
      "flags": {},
      "attributes": {}
    },
    {
      "kie_linking": [],
      "label": "临边防护",
      "score": null,
      "points": [
        [
          148.23529411764707,
          505.29411764705884
        ],
        [
          190.58823529411762,
          526.470588235294
        ],
        [
          209.41176470588232,
          557.0588235294117
        ],
        [
          212.94117647058823,
          645.2941176470588
        ],
        [
          208.23529411764707,
          790.0
        ],
        [
          205.88235294117646,
          1007.6470588235294
        ],
        [
          204.70588235294116,
          1074.7058823529412
        ],
        [
          240.0,
          1075.8823529411764
        ],
        [
          238.8235294117647,
          821.7647058823529
        ],
        [
          237.6470588235294,
          673.5294117647059
        ],
        [
          238.8235294117647,
          534.7058823529411
        ],
        [
          234.11764705882354,
          515.8823529411765
        ],
        [
          155.29411764705884,
          481.764705882353
        ]
      ],
      "group_id": null,
      "description": "",
      "difficult": false,
      "shape_type": "polygon",
      "flags": {},
      "attributes": {}
    },
    {
      "kie_linking": [],
      "label": "安全锥",
      "score": null,
      "points": [
        [
          270.5882352941176,
          786.470588235294
        ],
        [
          314.1176470588235,
          842.9411764705882
        ]
      ],
      "group_id": null,
      "description": "",
      "difficult": false,
      "shape_type": "rectangle",
      "flags": {},
      "attributes": {}
    },
    {
      "kie_linking": [],
      "label": "安全锥",
      "score": null,
      "points": [
        [
          265.88235294117646,
          817.0588235294117
        ],
        [
          315.29411764705884,
          884.1176470588235
        ]
      ],
      "group_id": null,
      "description": "",
      "difficult": false,
      "shape_type": "rectangle",
      "flags": {},
      "attributes": {}
    },
    {
      "kie_linking": [],
      "label": "安全锥",
      "score": null,
      "points": [
        [
          223.52941176470586,
          488.8235294117647
        ],
        [
          256.4705882352941,
          542.9411764705882
        ]
      ],
      "group_id": null,
      "description": "",
      "difficult": false,
      "shape_type": "rectangle",
      "flags": {},
      "attributes": {}
    },
    {
      "kie_linking": [],
      "label": "反光柱",
      "score": null,
      "points": [
        [
          1381.1764705882354,
          918.2352941176471
        ],
        [
          1425.8823529411766,
          1000.5882352941176
        ]
      ],
      "group_id": null,
      "description": "",
      "difficult": false,
      "shape_type": "rectangle",
      "flags": {},
      "attributes": {}
    },
    {
      "kie_linking": [],
      "label": "反光柱",
      "score": null,
      "points": [
        [
          1194.1176470588236,
          757.0588235294117
        ],
        [
          1229.4117647058824,
          840.5882352941176
        ]
      ],
      "group_id": null,
      "description": "",
      "difficult": false,
      "shape_type": "rectangle",
      "flags": {},
      "attributes": {}
    },
    {
      "kie_linking": [],
      "label": "反光柱",
      "score": null,
      "points": [
        [
          1056.4705882352941,
          657.0588235294117
        ],
        [
          1102.3529411764707,
          720.5882352941176
        ]
      ],
      "group_id": null,
      "description": "",
      "difficult": false,
      "shape_type": "rectangle",
      "flags": {},
      "attributes": {}
    },
    {
      "kie_linking": [],
      "label": "反光柱",
      "score": null,
      "points": [
        [
          961.1764705882354,
          567.6470588235294
        ],
        [
          995.2941176470588,
          634.7058823529411
        ]
      ],
      "group_id": null,
      "description": "",
      "difficult": false,
      "shape_type": "rectangle",
      "flags": {},
      "attributes": {}
    },
    {
      "kie_linking": [],
      "label": "反光柱",
      "score": null,
      "points": [
        [
          877.6470588235295,
          505.29411764705884
        ],
        [
          908.2352941176471,
          562.9411764705882
        ]
      ],
      "group_id": null,
      "description": "",
      "difficult": false,
      "shape_type": "rectangle",
      "flags": {},
      "attributes": {}
    },
    {
      "kie_linking": [],
      "label": "反光柱",
      "score": null,
      "points": [
        [
          815.2941176470588,
          454.7058823529412
        ],
        [
          843.5294117647059,
          501.764705882353
        ]
      ],
      "group_id": null,
      "description": "",
      "difficult": false,
      "shape_type": "rectangle",
      "flags": {},
      "attributes": {}
    },
    {
      "kie_linking": [],
      "label": "反光柱",
      "score": null,
      "points": [
        [
          715.2941176470588,
          371.1764705882353
        ],
        [
          738.8235294117646,
          414.7058823529412
        ]
      ],
      "group_id": null,
      "description": "",
      "difficult": false,
      "shape_type": "rectangle",
      "flags": {},
      "attributes": {}
    },
    {
      "kie_linking": [],
      "label": "反光柱",
      "score": null,
      "points": [
        [
          671.7647058823529,
          333.5294117647059
        ],
        [
          698.8235294117646,
          377.05882352941177
        ]
      ],
      "group_id": null,
      "description": "",
      "difficult": false,
      "shape_type": "rectangle",
      "flags": {},
      "attributes": {}
    },
    {
      "kie_linking": [],
      "label": "反光柱",
      "score": null,
      "points": [
        [
          637.6470588235295,
          294.70588235294116
        ],
        [
          658.8235294117646,
          335.88235294117646
        ]
      ],
      "group_id": null,
      "description": "",
      "difficult": false,
      "shape_type": "rectangle",
      "flags": {},
      "attributes": {}
    },
    {
      "kie_linking": [],
      "label": "反光柱",
      "score": null,
      "points": [
        [
          607.0588235294117,
          271.1764705882353
        ],
        [
          623.5294117647059,
          317.05882352941177
        ]
      ],
      "group_id": null,
      "description": "",
      "difficult": false,
      "shape_type": "rectangle",
      "flags": {},
      "attributes": {}
    },
    {
      "kie_linking": [],
      "label": "越野车",
      "score": null,
      "points": [
        [
          255.29411764705884,
          430.0
        ],
        [
          411.764705882353,
          581.7647058823529
        ]
      ],
      "group_id": null,
      "description": "",
      "difficult": false,
      "shape_type": "rectangle",
      "flags": {},
      "attributes": {}
    },
    {
      "label": "运输车",
      "score": null,
      "points": [
        [
          272.3255813953489,
          63.837209302325554
        ],
        [
          332.7906976744186,
          142.90697674418604
        ]
      ],
      "group_id": null,
      "description": "",
      "difficult": false,
      "shape_type": "rectangle",
      "flags": {},
      "attributes": {},
      "kie_linking": []
    }
  ],
  "imagePath": "dji_fly_20251112_100213_0_1762912933877_photo_low_quality.jpg",
  "imageData": null,
  "imageHeight": 1080,
  "imageWidth": 1440,
  "description": ""
}