{
  "version": "3.0.3",
  "flags": {},
  "shapes": [
    {
      "kie_linking": [],
      "label": "运输车",
      "score": null,
      "points": [
        [
          564.8000000000001,
          204.0
        ],
        [
          644.8000000000001,
          204.0
        ],
        [
          644.8000000000001,
          348.0
        ],
        [
          564.8000000000001,
          348.0
        ]
      ],
      "group_id": null,
      "description": "",
      "difficult": false,
      "shape_type": "rectangle",
      "flags": {},
      "attributes": {}
    },
    {
      "kie_linking": [],
      "label": "运输车",
      "score": null,
      "points": [
        [
          877.6,
          117.6
        ],
        [
          971.2,
          117.6
        ],
        [
          971.2,
          172.0
        ],
        [
          877.6,
          172.0
        ]
      ],
      "group_id": null,
      "description": "",
      "difficult": false,
      "shape_type": "rectangle",
      "flags": {},
      "attributes": {}
    },
    {
      "kie_linking": [],
      "label": "运输车",
      "score": null,
      "points": [
        [
          904.0,
          180.0
        ],
        [
          1005.6,
          180.0
        ],
        [
          1005.6,
          241.6
        ],
        [
          904.0,
          241.6
        ]
      ],
      "group_id": null,
      "description": "",
      "difficult": false,
      "shape_type": "rectangle",
      "flags": {},
      "attributes": {}
    },
    {
      "kie_linking": [],
      "label": "汽车",
      "score": null,
      "points": [
        [
          952.8,
          243.2
        ],
        [
          1037.6,
          243.2
        ],
        [
          1037.6,
          304.8
        ],
        [
          952.8,
          304.8
        ]
      ],
      "group_id": null,
      "description": "",
      "difficult": false,
      "shape_type": "rectangle",
      "flags": {},
      "attributes": {}
    },
    {
      "kie_linking": [],
      "label": "临边防护",
      "score": null,
      "points": [
        [
          1019.8675496688742,
          168.80794701986753
        ],
        [
          1025.8278145695365,
          151.58940397350992
        ],
        [
          1056.291390728477,
          242.31788079470195
        ],
        [
          1047.682119205298,
          256.887417218543
        ]
      ],
      "group_id": null,
      "description": "",
      "difficult": false,
      "shape_type": "polygon",
      "flags": {},
      "attributes": {}
    },
    {
      "label": "安全锥",
      "score": null,
      "points": [
        [
          975.0200803212851,
          144.17670682730923
        ],
        [
          980.6425702811244,
          144.17670682730923
        ],
        [
          980.6425702811244,
          155.42168674698794
        ],
        [
          975.0200803212851,
          155.42168674698794
        ]
      ],
      "group_id": null,
      "description": "",
      "difficult": false,
      "shape_type": "rectangle",
      "flags": {},
      "attributes": {},
      "kie_linking": []
    },
    {
      "label": "安全锥",
      "score": null,
      "points": [
        [
          982.2489959839357,
          140.96385542168673
        ],
        [
          991.0843373493976,
          140.96385542168673
        ],
        [
          991.0843373493976,
          154.61847389558233
        ],
        [
          982.2489959839357,
          154.61847389558233
        ]
      ],
      "group_id": null,
      "description": "",
      "difficult": false,
      "shape_type": "rectangle",
      "flags": {},
      "attributes": {},
      "kie_linking": []
    }
  ],
  "imagePath": "dji_fly_20251111_101003_0_1762827003509_photo_low_quality.jpg",
  "imageData": null,
  "imageHeight": 1080,
  "imageWidth": 1440,
  "description": ""
}