{
  "version": "3.0.3",
  "flags": {},
  "shapes": [
    {
      "kie_linking": [],
      "label": "反光衣",
      "score": null,
      "points": [
        [
          777.8761061946902,
          676.9911504424778
        ],
        [
          804.4247787610618,
          676.9911504424778
        ],
        [
          804.4247787610618,
          697.3451327433628
        ],
        [
          777.8761061946902,
          697.3451327433628
        ]
      ],
      "group_id": null,
      "description": "",
      "difficult": false,
      "shape_type": "rectangle",
      "flags": {},
      "attributes": {}
    },
    {
      "kie_linking": [],
      "label": "反光衣",
      "score": null,
      "points": [
        [
          703.5398230088495,
          831.858407079646
        ],
        [
          739.8230088495575,
          831.858407079646
        ],
        [
          739.8230088495575,
          860.1769911504424
        ],
        [
          703.5398230088495,
          860.1769911504424
        ]
      ],
      "group_id": null,
      "description": "",
      "difficult": false,
      "shape_type": "rectangle",
      "flags": {},
      "attributes": {}
    },
    {
      "kie_linking": [],
      "label": "人员",
      "score": null,
      "points": [
        [
          702.6548672566371,
          814.1592920353982
        ],
        [
          739.8230088495575,
          814.1592920353982
        ],
        [
          739.8230088495575,
          882.3008849557522
        ],
        [
          702.6548672566371,
          882.3008849557522
        ]
      ],
      "group_id": null,
      "description": "",
      "difficult": false,
      "shape_type": "rectangle",
      "flags": {},
      "attributes": {}
    },
    {
      "kie_linking": [],
      "label": "人员",
      "score": null,
      "points": [
        [
          765.4867256637167,
          662.8318584070796
        ],
        [
          800.8849557522124,
          662.8318584070796
        ],
        [
          800.8849557522124,
          714.1592920353982
        ],
        [
          765.4867256637167,
          714.1592920353982
        ]
      ],
      "group_id": null,
      "description": "",
      "difficult": false,
      "shape_type": "rectangle",
      "flags": {},
      "attributes": {}
    },
    {
      "kie_linking": [],
      "label": "安全锥",
      "score": null,
      "points": [
        [
          983.1858407079645,
          582.3008849557522
        ],
        [
          1018.5840707964601,
          582.3008849557522
        ],
        [
          1018.5840707964601,
          615.0442477876105
        ],
        [
          983.1858407079645,
          615.0442477876105
        ]
      ],
      "group_id": null,
      "description": "",
      "difficult": false,
      "shape_type": "rectangle",
      "flags": {},
      "attributes": {}
    },
    {
      "kie_linking": [],
      "label": "桥台围挡",
      "score": null,
      "points": [
        [
          983.1858407079645,
          608.8495575221239
        ],
        [
          831.858407079646,
          545.1327433628318
        ],
        [
          833.6283185840707,
          511.504424778761
        ],
        [
          1031.858407079646,
          323.8938053097345
        ],
        [
          1154.867256637168,
          356.6371681415929
        ],
        [
          1146.9026548672566,
          406.19469026548666
        ],
        [
          1032.7433628318583,
          373.4513274336283
        ],
        [
          868.1415929203539,
          538.9380530973451
        ],
        [
          979.646017699115,
          577.8761061946902
        ]
      ],
      "group_id": null,
      "description": "",
      "difficult": false,
      "shape_type": "polygon",
      "flags": {},
      "attributes": {}
    },
    {
      "kie_linking": [],
      "label": "安全标识",
      "score": null,
      "points": [
        [
          897.3451327433628,
          464.6017699115044
        ],
        [
          922.1238938053096,
          464.6017699115044
        ],
        [
          922.1238938053096,
          487.6106194690265
        ],
        [
          897.3451327433628,
          487.6106194690265
        ]
      ],
      "group_id": null,
      "description": "",
      "difficult": false,
      "shape_type": "rectangle",
      "flags": {},
      "attributes": {}
    },
    {
      "label": "电缆线",
      "score": null,
      "points": [
        [
          2.197802197802198,
          988.6446886446887
        ],
        [
          1.465201465201465,
          976.1904761904761
        ],
        [
          37.362637362637365,
          957.1428571428571
        ],
        [
          91.94139194139194,
          941.3919413919414
        ],
        [
          152.01465201465203,
          935.5311355311355
        ],
        [
          212.45421245421247,
          916.1172161172161
        ],
        [
          242.12454212454213,
          894.8717948717949
        ],
        [
          262.27106227106225,
          868.1318681318681
        ],
        [
          279.8534798534799,
          799.6336996336996
        ],
        [
          301.83150183150184,
          762.2710622710623
        ],
        [
          361.9047619047619,
          712.0879120879121
        ],
        [
          419.04761904761904,
          653.1135531135532
        ],
        [
          462.27106227106225,
          597.8021978021978
        ],
        [
          491.15384615384613,
          573.0769230769231
        ],
        [
          541.5384615384615,
          554.2307692307692
        ],
        [
          573.0769230769231,
          540.3846153846154
        ],
        [
          603.0769230769231,
          517.6923076923076
        ],
        [
          677.3076923076923,
          408.46153846153845
        ],
        [
          696.7654986522911,
          375.17520215633425
        ],
        [
          700.8086253369272,
          378.6792452830189
        ],
        [
          680.0539083557951,
          423.96226415094344
        ],
        [
          654.448160535117,
          469.5652173913043
        ],
        [
          628.3612040133779,
          505.01672240802674
        ],
        [
          597.9264214046823,
          535.1170568561872
        ],
        [
          546.7558528428094,
          560.5351170568562
        ],
        [
          496.92307692307696,
          583.6120401337793
        ],
        [
          474.5150501672241,
          600.0
        ],
        [
          442.40802675585286,
          640.4682274247491
        ],
        [
          408.29431438127096,
          683.9464882943143
        ],
        [
          355.78595317725757,
          732.7759197324414
        ],
        [
          312.64214046822747,
          766.8896321070233
        ],
        [
          295.2508361204014,
          788.963210702341
        ],
        [
          283.21070234113716,
          827.0903010033444
        ],
        [
          265.8193979933111,
          884.9498327759196
        ],
        [
          251.56682027649765,
          903.1336405529954
        ],
        [
          223.45622119815664,
          923.4101382488479
        ],
        [
          180.1382488479262,
          939.5391705069125
        ],
        [
          143.2718894009216,
          946.9124423963134
        ],
        [
          93.04147465437781,
          951.9815668202765
        ],
        [
          51.10599078341008,
          963.5023041474655
        ]
      ],
      "group_id": null,
      "description": "",
      "difficult": false,
      "shape_type": "polygon",
      "flags": {},
      "attributes": {},
      "kie_linking": []
    }
  ],
  "imagePath": "dji_fly_20251111_101256_0_1762827176987_photo_low_quality.jpg",
  "imageData": null,
  "imageHeight": 1080,
  "imageWidth": 1440,
  "description": ""
}